gse_alcli.py
src/__init__.py
src/gse_alcli.py
gse_alcli-0.0.1.post2.dist-info/METADATA
gse_alcli-0.0.1.post2.dist-info/WHEEL
gse_alcli-0.0.1.post2.dist-info/entry_points.txt
gse_alcli-0.0.1.post2.dist-info/top_level.txt
gse_alcli-0.0.1.post2.dist-info/RECORD
